clidoku/__init__.py
clidoku/enums.py
clidoku/game.py
clidoku/grid.py
clidoku/logging_config.py
clidoku/main.py
clidoku-0.1.2.dist-info/METADATA
clidoku-0.1.2.dist-info/WHEEL
clidoku-0.1.2.dist-info/entry_points.txt
clidoku-0.1.2.dist-info/licenses/LICENSE
clidoku-0.1.2.dist-info/RECORD
