Metadata-Version: 2.4
Name: clidoku
Version: 0.1.2
Summary: A simple command-line sudoku game
Author: Barney Jackson
License-File: LICENSE
Keywords: cli,game,puzzle,sudoku,terminal
Classifier: Development Status :: 4 - Beta
Classifier: Environment :: Console
Classifier: Intended Audience :: End Users/Desktop
Classifier: License :: OSI Approved :: BSD License
Classifier: Operating System :: OS Independent
Classifier: Programming Language :: Python :: 3
Classifier: Programming Language :: Python :: 3.12
Classifier: Topic :: Games/Entertainment :: Puzzle Games
Requires-Python: >=3.12
